bemm_gen/__init__.py
bemm_gen/convert.py
bemm_gen/make_param.py
bemm_gen/model.py
bemm_gen/protein.py
bemm_gen/utils.py
bemm_gen/share/FF_PARAM/FF_AMO/AMO.frcmod
bemm_gen/share/FF_PARAM/FF_AMO/AMO.lib
bemm_gen/share/FF_PARAM/FF_AMO/AMO.mol2
bemm_gen/share/FF_PARAM/FF_AMO/AMO.pdb
bemm_gen/share/FF_PARAM/FF_AMO/AMO_orig.mol2
bemm_gen/share/FF_PARAM/FF_AMO/AMO_orig_round.mol2
bemm_gen/share/FF_PARAM/FF_AMO/AMO_partialChgs.mol2
bemm_gen/share/FF_PARAM/FF_AMO/AMO_psi4.mol2
bemm_gen/share/FF_PARAM/FF_AMO/description.txt
bemm_gen/share/FF_PARAM/FF_AMO/leap.in
bemm_gen/share/FF_PARAM/FF_AMO/smiles.png
bemm_gen/share/FF_PARAM/FF_AMO/smiles.txt
bemm_gen/share/FF_PARAM/FF_AMO/smiles_ETKDGv3.png
bemm_gen/share/FF_PARAM/FF_AMO/smiles_charges.png
bemm_gen/share/FF_PARAM/FF_ARM/ARM.frcmod
bemm_gen/share/FF_PARAM/FF_ARM/ARM.lib
bemm_gen/share/FF_PARAM/FF_ARM/ARM.mol2
bemm_gen/share/FF_PARAM/FF_ARM/ARM.pdb
bemm_gen/share/FF_PARAM/FF_ARM/ARM_orig.mol2
bemm_gen/share/FF_PARAM/FF_ARM/ARM_orig_round.mol2
bemm_gen/share/FF_PARAM/FF_ARM/ARM_partialChgs.mol2
bemm_gen/share/FF_PARAM/FF_ARM/ARM_psi4.mol2
bemm_gen/share/FF_PARAM/FF_ARM/description.txt
bemm_gen/share/FF_PARAM/FF_ARM/leap.in
bemm_gen/share/FF_PARAM/FF_ARM/smiles.png
bemm_gen/share/FF_PARAM/FF_ARM/smiles.txt
bemm_gen/share/FF_PARAM/FF_ARM/smiles_ETKDGv3.png
bemm_gen/share/FF_PARAM/FF_ARM/smiles_charges.png
bemm_gen/share/FF_PARAM/FF_ARO/ARO.frcmod
bemm_gen/share/FF_PARAM/FF_ARO/ARO.lib
bemm_gen/share/FF_PARAM/FF_ARO/ARO.mol2
bemm_gen/share/FF_PARAM/FF_ARO/ARO.pdb
bemm_gen/share/FF_PARAM/FF_ARO/ARO_orig.mol2
bemm_gen/share/FF_PARAM/FF_ARO/ARO_orig_round.mol2
bemm_gen/share/FF_PARAM/FF_ARO/ARO_partialChgs.mol2
bemm_gen/share/FF_PARAM/FF_ARO/ARO_psi4.mol2
bemm_gen/share/FF_PARAM/FF_ARO/description.txt
bemm_gen/share/FF_PARAM/FF_ARO/leap.in
bemm_gen/share/FF_PARAM/FF_ARO/smiles.png
bemm_gen/share/FF_PARAM/FF_ARO/smiles.txt
bemm_gen/share/FF_PARAM/FF_ARO/smiles_ETKDGv3.png
bemm_gen/share/FF_PARAM/FF_ARO/smiles_charges.png
bemm_gen-2024.10.10.dist-info/LICENSE
bemm_gen-2024.10.10.dist-info/METADATA
bemm_gen-2024.10.10.dist-info/WHEEL
bemm_gen-2024.10.10.dist-info/entry_points.txt
bemm_gen-2024.10.10.dist-info/top_level.txt
bemm_gen-2024.10.10.dist-info/RECORD
