Metadata-Version: 2.1
Name: bemm-gen
Version: 2024.10.10
Summary: Biomolecular Environment Mimicking Model GENerator
Author-email: Takunori Yasuda <yasuda.takunori.tkb_gb@u.tsukuba.ac.jp>, Rikuri Morita <mriky.25@gmail.com>
License: MIT License
Project-URL: Homepage, https://github.com/y4suda/BEMM-GEN
Project-URL: Repository, https://github.com/y4suda/BEMM-GEN
Project-URL: Issues, https://github.com/y4suda/BEMM-GEN/issues
Keywords: bioinfomatic,molecular dynamics,biology,chemoinformatics
Classifier: Programming Language :: Python :: 3
Classifier: License :: OSI Approved :: MIT License
Classifier: Operating System :: OS Independent
Classifier: Development Status :: 4 - Beta
Requires-Python: >=3.9
License-File: LICENSE
Requires-Dist: scikit-learn
Requires-Dist: rdkit
Requires-Dist: parmed
